README.txt
setup.cfg
setup.py
collective/__init__.py
collective.wtf.egg-info/PKG-INFO
collective.wtf.egg-info/SOURCES.txt
collective.wtf.egg-info/dependency_links.txt
collective.wtf.egg-info/entry_points.txt
collective.wtf.egg-info/namespace_packages.txt
collective.wtf.egg-info/not-zip-safe
collective.wtf.egg-info/requires.txt
collective.wtf.egg-info/top_level.txt
collective/wtf/__init__.py
collective/wtf/config.py
collective/wtf/configure.zcml
collective/wtf/deserializer.py
collective/wtf/exportimport.py
collective/wtf/interfaces.py
collective/wtf/serializer.py
collective/wtf/utils.py
collective/wtf/verify.py
collective/wtf/Extensions/test_scripts.py
collective/wtf/browser/__init__.py
collective/wtf/browser/configure.zcml
collective/wtf/browser/roleinfo.py
collective/wtf/browser/sanitycheck.py
collective/wtf/browser/tocsv.py
collective/wtf/tests/__init__.py
collective/wtf/tests/test_exportimport.py
collective/wtf/tests/test_parsing.py
collective/wtf/tests/profiles/testing/workflow_csv/test_wf.csv
docs/HISTORY.txt
docs/INSTALL.txt
docs/TODO.txt