Metadata-Version: 1.0
Name: collective.wtf
Version: 1.0b9
Summary: GenericSetup importer and exporter for workflow definitions that uses CSV instead of XML
Home-page: http://plone.org
Author: Martin Aspeli
Author-email: optilude@gmail.com
License: LGPL
Keywords: plone workflow genericsetup
Platform: UNKNOWN
Classifier: Framework :: Plone
Classifier: Programming Language :: Python
Classifier: Topic :: Software Development :: Libraries :: Python Modules
